nxpd-0.2.0.dist-info/RECORD
nxpd-0.2.0.dist-info/WHEEL
nxpd-0.2.0.dist-info/top_level.txt
nxpd-0.2.0.dist-info/metadata.json
nxpd-0.2.0.dist-info/METADATA
nxpd-0.2.0.dist-info/DESCRIPTION.rst
nxpd/utils.py
nxpd/ipythonsupport.py
nxpd/nx_pydot.py
nxpd/__init__.py
nxpd/params.py
nxpd/pydot/__init__.py
nxpd/pydot/_dotparser.py
